laminar/__init__.py
laminar/laminar.py
laminar/laminar_examples.py
laminar_py-1.1.6.dist-info/LICENSE
laminar_py-1.1.6.dist-info/METADATA
laminar_py-1.1.6.dist-info/WHEEL
laminar_py-1.1.6.dist-info/top_level.txt
laminar_py-1.1.6.dist-info/RECORD
