Metadata-Version: 2.1
Name: laminar-py
Version: 1.1.6
Summary: Simpler parallelization.
Home-page: https://github.com/dgellerup/laminar
Download-URL: https://github.com/dgellerup/laminar/archive/v1.1.6.tar.gz
Author: Dane Gellerup
Author-email: danegellerup@uwalumni.com
Maintainer: Dane Gellerup
Maintainer-email: danegellerup@uwalumni.com
License: MIT
Keywords: laminar,laminar-pyparallel,parallelization,parallel processing,processing
Classifier: Development Status :: 5 - Production/Stable
Classifier: Intended Audience :: Developers
Classifier: Topic :: Software Development :: Build Tools
Classifier: License :: OSI Approved :: MIT License
Classifier: Programming Language :: Python :: 3
Classifier: Programming Language :: Python :: 3.6
Classifier: Programming Language :: Python :: 3.7
Classifier: Programming Language :: Python :: 3.8
License-File: LICENSE
Requires-Dist: pandas (>=0.24.0)
Requires-Dist: numpy (>=1.12.1)
